bothive/__init__.py
bothive/main.py
bothive-0.1.1.dist-info/LICENSE
bothive-0.1.1.dist-info/METADATA
bothive-0.1.1.dist-info/WHEEL
bothive-0.1.1.dist-info/top_level.txt
bothive-0.1.1.dist-info/RECORD
