Metadata-Version: 2.1
Name: bothive
Version: 0.1.1
Summary: A Python library for bots orchestration
Home-page: https://github.com/john-tavares/bothive
Author: Jonathan Tavares
Author-email: jonathantavares.all@gmail.com
License: MIT
Platform: UNKNOWN
License-File: LICENSE
